odoo/addons/session_db/README.rst
odoo/addons/session_db/__init__.py
odoo/addons/session_db/__manifest__.py
odoo/addons/session_db/pg_session_store.py
odoo/addons/session_db/i18n/it.po
odoo/addons/session_db/i18n/session_db.pot
odoo/addons/session_db/readme/DESCRIPTION.md
odoo/addons/session_db/readme/USAGE.md
odoo/addons/session_db/static/description/icon.png
odoo/addons/session_db/static/description/index.html
odoo/addons/session_db/tests/__init__.py
odoo/addons/session_db/tests/test_pg_session_store.py
odoo_addon_session_db-19.0.1.0.0.2.dist-info/METADATA
odoo_addon_session_db-19.0.1.0.0.2.dist-info/WHEEL
odoo_addon_session_db-19.0.1.0.0.2.dist-info/top_level.txt
odoo_addon_session_db-19.0.1.0.0.2.dist-info/RECORD
